MANIFEST.in
README.rst
setup.cfg
setup.py
luke_corp_pyunsplash.egg-info/PKG-INFO
luke_corp_pyunsplash.egg-info/SOURCES.txt
luke_corp_pyunsplash.egg-info/dependency_links.txt
luke_corp_pyunsplash.egg-info/requires.txt
luke_corp_pyunsplash.egg-info/top_level.txt
pyunsplash/__init__.py
pyunsplash/pyunsplash.py
pyunsplash/src/__init__.py
pyunsplash/src/collections.py
pyunsplash/src/liblogging.py
pyunsplash/src/photos.py
pyunsplash/src/rest.py
pyunsplash/src/search.py
pyunsplash/src/settings.py
pyunsplash/src/stats.py
pyunsplash/src/unobject.py
pyunsplash/src/unpage.py
pyunsplash/src/users.py